{
  "*": {
    "type": "page"
  },
  "index": {
    "title": "Головна",
    "display": "hidden",
    "theme": {
      "layout": "raw",
      "sidebar": false,
      "toc": true
    }
  },
  "game": {
    "title": "Гра",
    "theme": {
      "layout": "raw"
    }
  },
  "editor": {
    "title": "Редактор",
    "theme": {
      "layout": "raw"
    }
  },
  "blog": {
    "title": "Блог",
    "type": "page",
    "theme": {
      "sidebar": false
    }
  },
  "roadmap": {
    "title": "Дорожня карта",
    "type": "page"
  },
  "filling": {
    "title": "Наповнення",
    "type": "page",
    "display": "hidden"
  }
}
